qazaq_inflector/__init__.py
qazaq_inflector/inflector.py
qazaq_inflector-0.1.0.dist-info/licenses/LICENSE
qazaq_inflector-0.1.0.dist-info/METADATA
qazaq_inflector-0.1.0.dist-info/WHEEL
qazaq_inflector-0.1.0.dist-info/top_level.txt
qazaq_inflector-0.1.0.dist-info/RECORD
